datapizza/clients/google/__init__.py
datapizza/clients/google/google_client.py
datapizza/clients/google/memory_adapter.py
datapizza_ai_clients_google-0.0.7.dist-info/METADATA
datapizza_ai_clients_google-0.0.7.dist-info/WHEEL
datapizza_ai_clients_google-0.0.7.dist-info/RECORD
