Metadata-Version: 2.4
Name: datapizza-ai-clients-google
Version: 0.0.7
Summary: Google (Gemini) client for the datapizza-ai framework
License: MIT
Classifier: License :: OSI Approved :: MIT License
Classifier: Programming Language :: Python :: 3
Classifier: Topic :: Scientific/Engineering :: Artificial Intelligence
Classifier: Topic :: Software Development :: Libraries :: Application Frameworks
Requires-Python: <4,>=3.10.0
Requires-Dist: datapizza-ai-core<0.1.0,>=0.0.7
Requires-Dist: google-genai<2.0.0,>=1.3.0
